bengalinlp/__init__.py
bengalinlp/cleantext/__init__.py
bengalinlp/cleantext/clean.py
bengalinlp/cleantext/constants.py
bengalinlp/corpus/__init__.py
bengalinlp/corpus/_stopwords.py
bengalinlp/corpus/corpus.py
bengalinlp/embedding/__init__.py
bengalinlp/embedding/doc2vec.py
bengalinlp/embedding/fasttext.py
bengalinlp/embedding/glove.py
bengalinlp/embedding/word2vec.py
bengalinlp/token_classification/__init__.py
bengalinlp/token_classification/ner.py
bengalinlp/token_classification/pos.py
bengalinlp/token_classification/token_classification_trainer.py
bengalinlp/tokenizer/__init__.py
bengalinlp/tokenizer/basic.py
bengalinlp/tokenizer/nltk.py
bengalinlp/tokenizer/sentencepiece.py
bengalinlp/utils/__init__.py
bengalinlp/utils/config.py
bengalinlp/utils/downloader.py
bengalinlp/utils/utils.py
bengalinlp-2.0.1.dist-info/licenses/LICENSE
token_classification/__init__.py
token_classification/ner.py
token_classification/pos.py
token_classification/token_classification_trainer.py
tokenizer/__init__.py
tokenizer/basic.py
tokenizer/nltk.py
tokenizer/sentencepiece.py
bengalinlp-2.0.1.dist-info/METADATA
bengalinlp-2.0.1.dist-info/WHEEL
bengalinlp-2.0.1.dist-info/top_level.txt
bengalinlp-2.0.1.dist-info/RECORD
